rtsp/__doc__
rtsp/__init__.py
rtsp/ffmpegstream.py
rtsp-1.1.12.dist-info/LICENSE
rtsp-1.1.12.dist-info/METADATA
rtsp-1.1.12.dist-info/WHEEL
rtsp-1.1.12.dist-info/top_level.txt
rtsp-1.1.12.dist-info/RECORD
