Metadata-Version: 2.1
Name: rtsp
Version: 1.1.12
Summary: RTSP client wrapper around gstreamer/opencv
Home-page: https://github.com/statueofmike/rtsp
Author: Michael Stewart
Author-email: statueofmike@gmail.com
License: MIT
Download-URL: https://github.com/statueofmike/rtsp/archive/1.1.12.tar.gz
Keywords: rtsp image stream
Platform: UNKNOWN
Classifier: Development Status :: 4 - Beta
Classifier: License :: OSI Approved :: MIT License
Classifier: Programming Language :: Python :: 3
Classifier: Topic :: Multimedia :: Video
Classifier: Topic :: Multimedia :: Video :: Capture
Classifier: Topic :: System :: Networking
Requires-Python: >=3.5
License-File: LICENSE
